kaithem/.gitignore
kaithem/__init__.py
kaithem/__main__.py
kaithem/api/__init__.py
kaithem/api/apps_page.py
kaithem/api/chandler.py
kaithem/api/devices.py
kaithem/api/lifespan.py
kaithem/api/midi.py
kaithem/api/modules.py
kaithem/api/plugin_interfaces.py
kaithem/api/plugins.py
kaithem/api/resource_types.py
kaithem/api/settings.py
kaithem/api/tags.py
kaithem/api/users.py
kaithem/api/util.py
kaithem/api/web/__init__.py
kaithem/api/web/dialogs.py
kaithem/api/widgets.py
kaithem/data/__init__.py
kaithem/data/bip39.txt
kaithem/data/config-schema.yaml
kaithem/data/default_bashrc.sh
kaithem/data/default_configuration.yaml
kaithem/data/defaultusersettings.yaml
kaithem/data/gm_instruments.yaml
kaithem/data/modules/Beholder/__metadata__.yaml
kaithem/data/modules/Beholder/filesearch.html
kaithem/data/modules/Beholder/fswall.html
kaithem/data/modules/Beholder/hls.js.html
kaithem/data/modules/Beholder/main.py
kaithem/data/modules/Beholder/player.html
kaithem/data/modules/Beholder/rtplayer.html
kaithem/data/modules/Beholder/serve.html
kaithem/data/modules/Beholder/serve_jpg.html
kaithem/data/modules/Beholder/serve_mp4.html
kaithem/data/modules/Beholder/ui.html
kaithem/data/modules/Beholder/view_nvr.yaml
kaithem/data/modules/Examples/APIWidgets.html
kaithem/data/modules/Examples/CSS Framework.html
kaithem/data/modules/Examples/Dynamic Pages.html
kaithem/data/modules/Examples/Time Event.py
kaithem/data/modules/Examples/__metadata__.yaml
kaithem/data/quotes.yaml
kaithem/data/static/README.md
kaithem/data/static/fonts/AtkinsonHyperlegible/AtkinsonHyperlegible-Bold.ttf
kaithem/data/static/fonts/AtkinsonHyperlegible/AtkinsonHyperlegible-BoldItalic.ttf
kaithem/data/static/fonts/AtkinsonHyperlegible/AtkinsonHyperlegible-Italic.ttf
kaithem/data/static/fonts/AtkinsonHyperlegible/AtkinsonHyperlegible-Regular.ttf
kaithem/data/static/fonts/AtkinsonHyperlegible/OFL.txt
kaithem/data/static/fonts/DSEG/DSEG14ClassicMini-Italic.ttf
kaithem/data/static/fonts/FiraCode-Regular.woff2
kaithem-0.92.1.dist-info/WHEEL
kaithem-0.92.1.dist-info/entry_points.txt
kaithem-0.92.1.dist-info/RECORD
kaithem-0.92.1.dist-info/METADATA
