Metadata-Version: 2.3
Name: kaithem
Version: 0.92.1
Summary: Home/commercial automation server
License: GPL-3.0-or-later
Author: Daniel Dunn
Requires-Python: >=3.10,<4.0
Classifier: License :: OSI Approved :: GNU General Public License v3 or later (GPLv3+)
Classifier: Programming Language :: Python :: 3
Classifier: Programming Language :: Python :: 3.10
Classifier: Programming Language :: Python :: 3.11
Classifier: Programming Language :: Python :: 3.12
Classifier: Programming Language :: Python :: 3.13
Provides-Extra: dev
Provides-Extra: test
Requires-Dist: scullery (==0.3.1) ; python_version >= "3.10" and python_version < "4.0"
Requires-Dist: iot-devices (==0.25.0) ; python_version >= "3.10" and python_version < "4.0"
Requires-Dist: icemedia (==0.1.23) ; python_version >= "3.10" and python_version < "4.0"
Requires-Dist: nvrchannel (==0.1.7) ; python_version >= "3.10" and python_version < "4.0"
Requires-Dist: numpy (==2.2.6) ; python_version >= "3.10" and python_version < "4.0"
Requires-Dist: cheroot (==10.0.1) ; python_version >= "3.10" and python_version < "4.0"
Requires-Dist: mako (==1.3.10) ; python_version >= "3.10" and python_version < "4.0"
Requires-Dist: jinja2 (==3.1.6) ; python_version >= "3.10" and python_version < "4.0"
Requires-Dist: pam (==0.2.0) ; python_version >= "3.10" and python_version < "4.0"
Requires-Dist: msgpack (==1.1.1) ; python_version >= "3.10" and python_version < "4.0"
Requires-Dist: pyyaml (==6.0.2) ; python_version >= "3.10" and python_version < "4.0"
Requires-Dist: types-pyyaml (==6.0.12.20250822) ; python_version >= "3.10" and python_version < "4.0"
Requires-Dist: pytest (==8.4.1) ; python_version >= "3.10" and python_version < "4.0"
Requires-Dist: nmcli (==1.5.0) ; python_version >= "3.10" and python_version < "4.0"
Requires-Dist: apprise (==1.9.4) ; python_version >= "3.10" and python_version < "4.0"
Requires-Dist: ffmpeg-python (==0.2.0) ; python_version >= "3.10" and python_version < "4.0"
Requires-Dist: yappi (==1.6.10) ; python_version >= "3.10" and python_version < "4.0"
Requires-Dist: zeroconf (==0.147.0) ; python_version >= "3.10" and python_version < "4.0"
Requires-Dist: colorzero (==2.0) ; python_version >= "3.10" and python_version < "4.0"
Requires-Dist: tinytag (==2.1.2) ; python_version >= "3.10" and python_version < "4.0"
Requires-Dist: jsonschema (==4.25.1) ; python_version >= "3.10" and python_version < "4.0"
Requires-Dist: pint (==0.24.4) ; python_version >= "3.10" and python_version < "4.0"
Requires-Dist: pyflakes (==3.4.0) ; python_version >= "3.10" and python_version < "4.0"
Requires-Dist: python-mpv-jsonipc (==1.2.1) ; python_version >= "3.10" and python_version < "4.0"
Requires-Dist: textdistance (==4.6.3) ; python_version >= "3.10" and python_version < "4.0"
Requires-Dist: toml (==0.10.2) ; python_version >= "3.10" and python_version < "4.0"
Requires-Dist: vignette (==5.1.1) ; python_version >= "3.10" and python_version < "4.0"
Requires-Dist: simpleeval (==1.0.3) ; python_version >= "3.10" and python_version < "4.0"
Requires-Dist: websockets (==13.1) ; python_version >= "3.10" and python_version < "4.0"
Requires-Dist: zeep (==4.3.1) ; python_version >= "3.10" and python_version < "4.0"
Requires-Dist: passlib (==1.7.4) ; python_version >= "3.10" and python_version < "4.0"
Requires-Dist: pillow (==11.3.0) ; python_version >= "3.10" and python_version < "4.0"
Requires-Dist: evdev (==1.9.2) ; python_version >= "3.10" and python_version < "4.0"
Requires-Dist: markupsafe (==3.0.2) ; python_version >= "3.10" and python_version < "4.0"
Requires-Dist: types-requests (==2.32.4.20250809) ; python_version >= "3.10" and python_version < "4.0"
Requires-Dist: python-dateutil (==2.9.0.post0) ; python_version >= "3.10" and python_version < "4.0"
Requires-Dist: recurrent (==0.4.1) ; python_version >= "3.10" and python_version < "4.0"
Requires-Dist: pygments (==2.19.2) ; python_version >= "3.10" and python_version < "4.0"
Requires-Dist: pytz (==2025.2) ; python_version >= "3.10" and python_version < "4.0"
Requires-Dist: ntplib (==0.4.0) ; python_version >= "3.10" and python_version < "4.0"
Requires-Dist: holidays (==0.79) ; python_version >= "3.10" and python_version < "4.0"
Requires-Dist: pyserial (==3.5) ; python_version >= "3.10" and python_version < "4.0"
Requires-Dist: pygrep (==0.3.2) ; python_version >= "3.10" and python_version < "4.0"
Requires-Dist: python-rtmidi (==1.5.8) ; python_version >= "3.10" and python_version < "4.0"
Requires-Dist: paho-mqtt (==2.1.0) ; python_version >= "3.10" and python_version < "4.0"
Requires-Dist: setproctitle (==1.3.6) ; python_version >= "3.10" and python_version < "4.0"
Requires-Dist: psutil (==7.0.0) ; python_version >= "3.10" and python_version < "4.0"
Requires-Dist: netifaces (==0.11.0) ; python_version >= "3.10" and python_version < "4.0"
Requires-Dist: jack-client (==0.5.5) ; python_version >= "3.10" and python_version < "4.0"
Requires-Dist: sf2utils (==1.0.0) ; python_version >= "3.10" and python_version < "4.0"
Requires-Dist: scipy (==1.15.3) ; python_version >= "3.10" and python_version < "4.0"
Requires-Dist: attrs (==25.3.0) ; python_version >= "3.10" and python_version < "4.0"
Requires-Dist: beartype (==0.18.5) ; python_version >= "3.10" and python_version < "4.0"
Requires-Dist: types-jsonschema (==4.25.1.20250822) ; python_version >= "3.10" and python_version < "4.0"
Requires-Dist: stamina (==24.2.0) ; python_version >= "3.10" and python_version < "4.0"
Requires-Dist: stream-zip (==0.0.71) ; python_version >= "3.10" and python_version < "4.0"
Requires-Dist: argon2-cffi (==23.1.0) ; python_version >= "3.10" and python_version < "4.0"
Requires-Dist: msgpack-types (==0.2.0) ; python_version >= "3.10" and python_version < "4.0"
Requires-Dist: niquests (==3.15.2) ; python_version >= "3.10" and python_version < "4.0"
Requires-Dist: quart (==0.20.0) ; python_version >= "3.10" and python_version < "4.0"
Requires-Dist: hypercorn (==0.17.3) ; python_version >= "3.10" and python_version < "4.0"
Requires-Dist: structlog (==24.4.0) ; python_version >= "3.10" and python_version < "4.0"
Requires-Dist: rich (==14.1.0) ; python_version >= "3.10" and python_version < "4.0"
Requires-Dist: colorama (==0.4.6) ; python_version >= "3.10" and python_version < "4.0"
Requires-Dist: starlette (==0.47.3) ; python_version >= "3.10" and python_version < "4.0"
Requires-Dist: ephem (==4.2) ; python_version >= "3.10" and python_version < "4.0"
Requires-Dist: opencv-python (==4.10.0.84) ; python_version >= "3.10" and python_version < "4.0"
Requires-Dist: pipewire-python (==0.2.3) ; python_version >= "3.10" and python_version < "4.0"
Requires-Dist: sherpa-onnx (==1.12.10) ; python_version >= "3.10" and python_version < "4.0"
Requires-Dist: soundfile (==0.13.1) ; python_version >= "3.10" and python_version < "4.0"
Requires-Dist: pygount (==3.1.0) ; python_version >= "3.10" and python_version < "4" and extra == "dev"
Requires-Dist: handsdown (==2.1.0) ; python_version >= "3.10" and python_version < "4.0" and extra == "dev"
Requires-Dist: pytest-cov (==5.0.0) ; python_version >= "3.10" and python_version < "4.0" and (extra == "dev" or extra == "test")
Requires-Dist: pytest-asyncio (==0.23.8) ; python_version >= "3.10" and python_version < "4.0" and (extra == "dev" or extra == "test")
Requires-Dist: time-machine (==2.19.0) ; python_version >= "3.10" and python_version < "4.0" and (extra == "dev" or extra == "test")
Requires-Dist: coverage (==7.10.6) ; python_version >= "3.10" and python_version < "4.0" and (extra == "dev" or extra == "test")
Requires-Dist: aioesphomeapi (==24.6.0) ; python_version >= "3.10" and python_version < "4.0"
Requires-Dist: aiomqtt (==2.4.0) ; python_version >= "3.10" and python_version < "4.0"
Requires-Dist: aiostream (==0.7.0) ; python_version >= "3.10" and python_version < "4.0"
Requires-Dist: bleak (==1.1.0) ; python_version >= "3.10" and python_version < "4.0"
Requires-Dist: cryptography (==45.0.6) ; python_version >= "3.10" and python_version < "4.0"
Requires-Dist: gpiozero (==2.0.1) ; python_version >= "3.10" and python_version < "4.0"
Requires-Dist: gpsdclient (==1.3.2) ; python_version >= "3.10" and python_version < "4.0"
Requires-Dist: urwid (==3.0.2) ; python_version >= "3.10" and python_version < "4.0"
Requires-Dist: uvicorn (==0.34.3) ; python_version >= "3.10" and python_version < "4.0"
Requires-Dist: yeelight (==0.7.16) ; python_version >= "3.10" and python_version < "4.0"
Requires-Dist: jaraco-functools (==4.3.0) ; python_version >= "3.10" and python_version < "4.0"
Requires-Dist: more-itertools (==10.7.0) ; python_version >= "3.10" and python_version < "4.0"
Requires-Dist: python-pam (==2.0.2) ; python_version >= "3.10" and python_version < "4.0"
Requires-Dist: exceptiongroup (==1.3.0) ; python_version == "3.10"
Requires-Dist: iniconfig (==2.1.0) ; python_version >= "3.10" and python_version < "4.0"
Requires-Dist: packaging (==25.0) ; python_version >= "3.10" and python_version < "4.0"
Requires-Dist: pluggy (==1.6.0) ; python_version >= "3.10" and python_version < "4.0"
Requires-Dist: tomli (==2.2.1) ; python_full_version <= "3.11.0a6" and python_version >= "3.10"
Requires-Dist: certifi (==2025.8.3) ; python_version >= "3.10" and python_version < "4.0"
Requires-Dist: click (==8.2.1) ; python_version >= "3.10" and python_version < "4.0"
Requires-Dist: markdown (==3.8.2) ; python_version >= "3.10" and python_version < "4.0"
Requires-Dist: requests (==2.32.5) ; python_version >= "3.10" and python_version < "4.0"
Requires-Dist: requests-oauthlib (==2.0.0) ; python_version >= "3.10" and python_version < "4.0"
Requires-Dist: future (==1.0.0) ; python_version >= "3.10" and python_version < "4.0"
Requires-Dist: ifaddr (==0.2.0) ; python_version >= "3.10" and python_version < "4.0"
Requires-Dist: setuptools (==80.9.0) ; python_version >= "3.10" and python_version < "4.0"
Requires-Dist: jsonschema-specifications (==2025.4.1) ; python_version >= "3.10" and python_version < "4.0"
Requires-Dist: referencing (==0.36.2) ; python_version >= "3.10" and python_version < "4.0"
Requires-Dist: rpds-py (==0.27.1) ; python_version >= "3.10" and python_version < "4.0"
Requires-Dist: flexcache (==0.3) ; python_version >= "3.10" and python_version < "4.0"
Requires-Dist: flexparser (==0.4) ; python_version >= "3.10" and python_version < "4.0"
Requires-Dist: platformdirs (==4.4.0) ; python_version >= "3.10" and python_version < "4.0"
Requires-Dist: typing-extensions (==4.15.0) ; python_version >= "3.10" and python_version < "4.0"
Requires-Dist: python-magic (==0.4.27) ; python_version >= "3.10" and python_version < "4.0"
Requires-Dist: isodate (==0.7.2) ; python_version >= "3.10" and python_version < "4.0"
Requires-Dist: lxml (==6.0.1) ; python_version >= "3.10" and python_version < "4.0"
Requires-Dist: requests-file (==2.1.0) ; python_version >= "3.10" and python_version < "4.0"
Requires-Dist: requests-toolbelt (==1.0.0) ; python_version >= "3.10" and python_version < "4.0"
Requires-Dist: urllib3 (==2.5.0) ; python_version >= "3.10" and python_version < "4.0"
Requires-Dist: six (==1.17.0) ; python_version >= "3.10" and python_version < "4.0"
Requires-Dist: parsedatetime (==2.6) ; python_version >= "3.10" and python_version < "4.0"
Requires-Dist: cffi (==1.17.1) ; python_version >= "3.10" and python_version < "4.0"
Requires-Dist: tenacity (==9.1.2) ; python_version >= "3.10" and python_version < "4.0"
Requires-Dist: pycryptodome (==3.23.0) ; python_version >= "3.10" and python_version < "4.0"
Requires-Dist: argon2-cffi-bindings (==25.1.0) ; python_version >= "3.10" and python_version < "4.0"
Requires-Dist: charset-normalizer (==3.4.3) ; python_version >= "3.10" and python_version < "4.0"
Requires-Dist: urllib3-future (==2.13.906) ; python_version >= "3.10" and python_version < "4.0"
Requires-Dist: wassima (==1.2.2) ; python_version >= "3.10" and python_version < "4.0"
Requires-Dist: aiofiles (==24.1.0) ; python_version >= "3.10" and python_version < "4.0"
Requires-Dist: blinker (==1.9.0) ; python_version >= "3.10" and python_version < "4.0"
Requires-Dist: flask (==3.1.2) ; python_version >= "3.10" and python_version < "4.0"
Requires-Dist: itsdangerous (==2.2.0) ; python_version >= "3.10" and python_version < "4.0"
Requires-Dist: werkzeug (==3.1.3) ; python_version >= "3.10" and python_version < "4.0"
Requires-Dist: h11 (==0.16.0) ; python_version >= "3.10" and python_version < "4.0"
Requires-Dist: h2 (==4.3.0) ; python_version >= "3.10" and python_version < "4.0"
Requires-Dist: priority (==2.0.0) ; python_version >= "3.10" and python_version < "4.0"
Requires-Dist: taskgroup (==0.2.2) ; python_version == "3.10"
Requires-Dist: uvloop (==0.21.0) ; platform_system != "Windows" and python_version >= "3.10" and python_version < "4.0"
Requires-Dist: wsproto (==1.2.0) ; python_version >= "3.10" and python_version < "4.0"
Requires-Dist: markdown-it-py (==4.0.0) ; python_version >= "3.10" and python_version < "4.0"
Requires-Dist: anyio (==4.10.0) ; python_version >= "3.10" and python_version < "4.0"
Requires-Dist: sherpa-onnx-core (==1.12.10) ; python_version >= "3.10" and python_version < "4.0"
Requires-Dist: chardet (==5.2.0) ; python_version >= "3.10" and python_version < "4" and extra == "dev"
Requires-Dist: gitpython (==3.1.45) ; python_version >= "3.10" and python_version < "4" and extra == "dev"
Requires-Dist: black (==25.1.0) ; python_version >= "3.10" and python_version < "4.0" and extra == "dev"
Requires-Dist: importlib-resources (==6.5.2) ; python_version >= "3.10" and python_version < "4.0" and extra == "dev"
Requires-Dist: pip (==25.2) ; python_version >= "3.10" and python_version < "4.0" and extra == "dev"
Requires-Dist: typed-ast (==1.5.5) ; python_version >= "3.10" and python_version < "4.0" and extra == "dev"
Requires-Dist: aiohappyeyeballs (==2.6.1) ; python_version >= "3.10" and python_version < "4.0"
Requires-Dist: async-interrupt (==1.2.2) ; python_version >= "3.10" and python_version < "4.0"
Requires-Dist: async-timeout (==5.0.1) ; python_version == "3.10"
Requires-Dist: chacha20poly1305-reuseable (==0.13.2) ; python_version >= "3.10" and python_version < "4.0"
Requires-Dist: noiseprotocol (==0.3.1) ; python_version >= "3.10" and python_version < "4.0"
Requires-Dist: protobuf (==6.32.0) ; python_version >= "3.10" and python_version < "4.0"
Requires-Dist: dbus-fast (==2.44.3) ; python_version >= "3.10" and python_version < "4.0" and platform_system == "Linux"
Requires-Dist: pyobjc-core (==11.1) ; python_version >= "3.10" and python_version < "4.0" and platform_system == "Darwin"
Requires-Dist: pyobjc-framework-corebluetooth (==11.1) ; python_version >= "3.10" and python_version < "4.0" and platform_system == "Darwin"
Requires-Dist: pyobjc-framework-libdispatch (==11.1) ; python_version >= "3.10" and python_version < "4.0" and platform_system == "Darwin"
Requires-Dist: winrt-runtime (==3.2.1) ; python_version >= "3.10" and python_version < "4.0" and platform_system == "Windows"
Requires-Dist: winrt-windows-devices-bluetooth (==3.2.1) ; python_version >= "3.10" and python_version < "4.0" and platform_system == "Windows"
Requires-Dist: winrt-windows-devices-bluetooth-advertisement (==3.2.1) ; python_version >= "3.10" and python_version < "4.0" and platform_system == "Windows"
Requires-Dist: winrt-windows-devices-bluetooth-genericattributeprofile (==3.2.1) ; python_version >= "3.10" and python_version < "4.0" and platform_system == "Windows"
Requires-Dist: winrt-windows-devices-enumeration (==3.2.1) ; python_version >= "3.10" and python_version < "4.0" and platform_system == "Windows"
Requires-Dist: winrt-windows-foundation (==3.2.1) ; python_version >= "3.10" and python_version < "4.0" and platform_system == "Windows"
Requires-Dist: winrt-windows-foundation-collections (==3.2.1) ; python_version >= "3.10" and python_version < "4.0" and platform_system == "Windows"
Requires-Dist: winrt-windows-storage-streams (==3.2.1) ; python_version >= "3.10" and python_version < "4.0" and platform_system == "Windows"
Requires-Dist: wcwidth (==0.2.13) ; python_version >= "3.10" and python_version < "4.0"
Requires-Dist: idna (==3.10) ; python_version >= "3.10" and python_version < "4.0"
Requires-Dist: oauthlib (==3.3.1) ; python_version >= "3.10" and python_version < "4.0"
Requires-Dist: pycparser (==2.22) ; python_version >= "3.10" and python_version < "4.0"
Requires-Dist: jh2 (==5.0.9) ; python_version >= "3.10" and python_version < "4.0"
Requires-Dist: qh3 (==1.5.4) ; python_version >= "3.10" and (platform_system == "Darwin" or platform_system == "Windows" or platform_system == "Linux") and (platform_machine == "x86_64" or platform_machine == "s390x" or platform_machine == "armv7l" or platform_machine == "ppc64le" or platform_machine == "ppc64" or platform_machine == "AMD64" or platform_machine == "aarch64" or platform_machine == "arm64" or platform_machine == "ARM64" or platform_machine == "x86" or platform_machine == "i686") a
Requires-Dist: hpack (==4.1.0) ; python_version >= "3.10" and python_version < "4.0"
Requires-Dist: hyperframe (==6.1.0) ; python_version >= "3.10" and python_version < "4.0"
Requires-Dist: mdurl (==0.1.2) ; python_version >= "3.10" and python_version < "4.0"
Requires-Dist: sniffio (==1.3.1) ; python_version >= "3.10" and python_version < "4.0"
Requires-Dist: gitdb (==4.0.12) ; python_version >= "3.10" and python_version < "4" and extra == "dev"
Requires-Dist: mypy-extensions (==1.1.0) ; python_version >= "3.10" and python_version < "4.0" and extra == "dev"
Requires-Dist: pathspec (==0.12.1) ; python_version >= "3.10" and python_version < "4.0" and extra == "dev"
Requires-Dist: pyobjc-framework-cocoa (==11.1) ; python_version >= "3.10" and python_version < "4.0" and platform_system == "Darwin"
Requires-Dist: smmap (==5.0.2) ; python_version >= "3.10" and python_version < "4" and extra == "dev"
